MANIFEST.in
README
setup.py
docs/CHANGELOG
docs/COPYING
docs/INSTALL
docs/LICENSE-2.0.txt
other/setcolor.c
other/setcolor.exe
src/testoob/__init__.py
src/testoob/asserter.py
src/testoob/capabilities.py
src/testoob/collecting.py
src/testoob/coverage.py
src/testoob/exceptions.py
src/testoob/extracting.py
src/testoob/main.py
src/testoob/profiling.py
src/testoob/run_cmd.py
src/testoob/test_loaders.py
src/testoob/testing.py
src/testoob/testoob
src/testoob/utils.py
src/testoob.egg-info/PKG-INFO
src/testoob.egg-info/SOURCES.txt
src/testoob.egg-info/dependency_links.txt
src/testoob.egg-info/top_level.txt
src/testoob/commandline/__init__.py
src/testoob/commandline/bgcolor_option.py
src/testoob/commandline/color_mode_option.py
src/testoob/commandline/glob_option.py
src/testoob/commandline/html_option.py
src/testoob/commandline/immediate_option.py
src/testoob/commandline/list_option.py
src/testoob/commandline/parsing.py
src/testoob/commandline/pbar_option.py
src/testoob/commandline/pdf_option.py
src/testoob/commandline/processes_option.py
src/testoob/commandline/randomize_option.py
src/testoob/commandline/regex_option.py
src/testoob/commandline/repeat_option.py
src/testoob/commandline/silent_option.py
src/testoob/commandline/time_each_test_option.py
src/testoob/commandline/timed_repeat_option.py
src/testoob/commandline/xml_option.py
src/testoob/compatibility/SimpleXMLWriter.py
src/testoob/compatibility/__init__.py
src/testoob/compatibility/itertools.py
src/testoob/compatibility/optparse.py
src/testoob/compatibility/sets.py
src/testoob/compatibility/subprocess.py
src/testoob/compatibility/textwrap.py
src/testoob/compatibility/trace.py
src/testoob/reporting/__init__.py
src/testoob/reporting/base.py
src/testoob/reporting/color_support.py
src/testoob/reporting/colored.py
src/testoob/reporting/common.py
src/testoob/reporting/err_info.py
src/testoob/reporting/html.py
src/testoob/reporting/html_standalone.py
src/testoob/reporting/html_xsl.py
src/testoob/reporting/html_xslt.py
src/testoob/reporting/options.py
src/testoob/reporting/pdf.py
src/testoob/reporting/progress_bar.py
src/testoob/reporting/reporter_proxy.py
