Metadata-Version: 1.0
Name: testoob
Version: 1.15
Summary: Testoob - An advanced unit testing framework
Home-page: http://code.google.com/p/testoob
Author: Ori Peleg
Author-email: testoob@gmail.com
License: Apache License, Version 2.0
Download-URL: http://sourceforge.net/project/showfiles.php?group_id=138557
Platform: any
Classifier: Development Status :: 5 - Production/Stable
Classifier: Environment :: Console
Classifier: Intended Audience :: Developers
Classifier: License :: OSI Approved :: Apache Software License
Classifier: Operating System :: OS Independent
Classifier: Operating System :: Microsoft :: Windows
Classifier: Operating System :: POSIX
Classifier: Programming Language :: Python
Classifier: Topic :: Software Development :: Quality Assurance
Classifier: Topic :: Software Development :: Testing
